roma/__init__.py
roma/euler.py
roma/internal.py
roma/mappings.py
roma/transforms.py
roma/utils.py
roma-1.5.4.dist-info/licenses/LICENSE
roma-1.5.4.dist-info/licenses/NOTICE
roma-1.5.4.dist-info/METADATA
roma-1.5.4.dist-info/WHEEL
roma-1.5.4.dist-info/top_level.txt
roma-1.5.4.dist-info/RECORD
