Metadata-Version: 2.4
Name: roma
Version: 1.5.4
Summary: A lightweight library to deal with 3D rotations in PyTorch.
Home-page: https://github.com/naver/roma
Author: Romain Brégier
Author-email: romain.bregier@naverlabs.com
Classifier: Programming Language :: Python :: 3
Classifier: License :: OSI Approved :: BSD License
Classifier: Operating System :: OS Independent
Requires-Python: >=3.6
License-File: LICENSE
License-File: NOTICE
Dynamic: author
Dynamic: author-email
Dynamic: classifier
Dynamic: description
Dynamic: description-content-type
Dynamic: home-page
Dynamic: license-file
Dynamic: requires-python
Dynamic: summary
